Metadata-Version: 2.1
Name: pycrime
Version: 0.0.6
Summary: Fetch crime statistics from the ExpenseCheck crime statistics API.
Home-page: https://github.com/furious-luke/pycrime
Author: Luke Hodkinson
Author-email: furious.luke@gmail.com
Maintainer: Luke Hodkinson
Maintainer-email: furious.luke@gmail.com
License: UNKNOWN
Platform: UNKNOWN
Classifier: Development Status :: 3 - Alpha
Classifier: Intended Audience :: Developers
Classifier: Natural Language :: English
Classifier: Operating System :: OS Independent
Classifier: Programming Language :: Python
Classifier: Programming Language :: Python :: 3.7
Classifier: License :: OSI Approved :: MIT License
